odoo/addons/account_reconciliation_widget_due_date/README.rst
odoo/addons/account_reconciliation_widget_due_date/__init__.py
odoo/addons/account_reconciliation_widget_due_date/__manifest__.py
odoo/addons/account_reconciliation_widget_due_date/i18n/account_reconciliation_widget_due_date.pot
odoo/addons/account_reconciliation_widget_due_date/i18n/es.po
odoo/addons/account_reconciliation_widget_due_date/models/__init__.py
odoo/addons/account_reconciliation_widget_due_date/models/account_bank_statement_line.py
odoo/addons/account_reconciliation_widget_due_date/models/reconciliation_widget.py
odoo/addons/account_reconciliation_widget_due_date/readme/CONTRIBUTORS.rst
odoo/addons/account_reconciliation_widget_due_date/readme/DESCRIPTION.rst
odoo/addons/account_reconciliation_widget_due_date/readme/USAGE.rst
odoo/addons/account_reconciliation_widget_due_date/static/description/icon.png
odoo/addons/account_reconciliation_widget_due_date/static/description/index.html
odoo/addons/account_reconciliation_widget_due_date/static/src/js/reconciliation_action.js
odoo/addons/account_reconciliation_widget_due_date/static/src/js/reconciliation_model.js
odoo/addons/account_reconciliation_widget_due_date/static/src/js/reconciliation_renderer.js
odoo/addons/account_reconciliation_widget_due_date/tests/__init__.py
odoo/addons/account_reconciliation_widget_due_date/tests/test_account_reconciliation_widget_date_due.py
odoo/addons/account_reconciliation_widget_due_date/views/account_bank_statement_line_view.xml
odoo_addon_account_reconciliation_widget_due_date-15.0.1.0.1.dist-info/METADATA
odoo_addon_account_reconciliation_widget_due_date-15.0.1.0.1.dist-info/WHEEL
odoo_addon_account_reconciliation_widget_due_date-15.0.1.0.1.dist-info/top_level.txt
odoo_addon_account_reconciliation_widget_due_date-15.0.1.0.1.dist-info/RECORD
